{
  "unpublishedPage": {
    "name": "Formulier - Werkplekinspectie",
    "slug": "formulier-werkplekinspectie",
    "layouts": [
      {
        "viewMode": false,
        "dsl": {
          "widgetName": "MainContainer",
          "backgroundColor": "none",
          "rightColumn": 1224,
          "snapColumns": 64,
          "detachFromLayout": true,
          "widgetId": "0",
          "topRow": 0,
          "bottomRow": 2050,
          "containerStyle": "none",
          "snapRows": 79,
          "parentRowSpace": 1,
          "type": "CANVAS_WIDGET",
          "canExtend": true,
          "version": 71,
          "minHeight": 800,
          "parentColumnSpace": 1,
          "dynamicBindingPathList": [],
          "leftColumn": 0,
          "children": [
            {
              "boxShadow": "none",
              "widgetName": "Header",
              "borderColor": "#E0DEDE",
              "isCanvas": true,
              "displayName": "Container",
              "iconSVG": "/static/media/icon.1977dca3370505e2db3a8e44cfd54907.svg",
              "searchTags": [
                "div",
                "parent",
                "group"
              ],
              "topRow": 0,
              "bottomRow": 20,
              "parentRowSpace": 10,
              "type": "CONTAINER_WIDGET",
              "hideCard": false,
              "shouldScrollContents": true,
              "animateLoading": true,
              "parentColumnSpace": 20.0625,
              "dynamicTriggerPathList": [],
              "leftColumn": 0,
              "dynamicBindingPathList": [
                {
                  "key": "borderRadius"
                }
              ],
              "children": [
                {
                  "widgetName": "Canvas1Copy",
                  "displayName": "Canvas",
                  "topRow": 0,
                  "bottomRow": 200,
                  "parentRowSpace": 1,
                  "type": "CANVAS_WIDGET",
                  "canExtend": false,
                  "hideCard": true,
                  "minHeight": 200,
                  "parentColumnSpace": 1,
                  "leftColumn": 0,
                  "dynamicBindingPathList": [],
                  "children": [
                    {
                      "boxShadow": "none",
                      "widgetName": "Image2Copy",
                      "displayName": "Image",
                      "iconSVG": "/static/media/icon.52d8fb963abcb95c79b10f1553389f22.svg",
                      "topRow": 0,
                      "bottomRow": 12,
                      "parentRowSpace": 10,
                      "type": "IMAGE_WIDGET",
                      "hideCard": false,
                      "animateLoading": true,
                      "parentColumnSpace": 19.75,
                      "dynamicTriggerPathList": [],
                      "imageShape": "RECTANGLE",
                      "leftColumn": 0,
                      "dynamicBindingPathList": [
                        {
                          "key": "borderRadius"
                        }
                      ],
                      "defaultImage": "https://www.vargar.eu/wp-content/uploads/2022/10/cropped-LOGO.png",
                      "key": "ewv4dytspe",
                      "image": "https://www.vargar.eu/wp-content/uploads/2022/10/cropped-LOGO.png",
                      "isDeprecated": false,
                      "rightColumn": 10,
                      "objectFit": "contain",
                      "widgetId": "ws7c3f6i9q",
                      "isVisible": true,
                      "version": 1,
                      "parentId": "016zeofrwo",
                      "renderMode": "CANVAS",
                      "isLoading": false,
                      "maxZoomLevel": 1,
                      "enableDownload": false,
                      "borderRadius": "{{appsmith.theme.borderRadius.appBorderRadius}}",
                      "enableRotation": false
                    },
                    {
                      "widgetName": "Text2",
                      "dynamicPropertyPathList": [],
                      "displayName": "Text",
                      "iconSVG": "/static/media/icon.97c59b523e6f70ba6f40a10fc2c7c5b5.svg",
                      "searchTags": [
                        "typography",
                        "paragraph",
                        "label"
                      ],
                      "topRow": 3,
                      "bottomRow": 10,
                      "parentRowSpace": 10,
                      "type": "TEXT_WIDGET",
                      "hideCard": false,
                      "animateLoading": true,
                      "overflow": "NONE",
                      "fontFamily": "{{appsmith.theme.fontFamily.appFont}}",
                      "parentColumnSpace": 20.0625,
                      "dynamicTriggerPathList": [],
                      "leftColumn": 10,
                      "dynamicBindingPathList": [
                        {
                          "key": "truncateButtonColor"
                        },
                        {
                          "key": "fontFamily"
                        },
                        {
                          "key": "borderRadius"
                        }
                      ],
                      "shouldTruncate": false,
                      "truncateButtonColor": "{{appsmith.theme.colors.primaryColor}}",
                      "text": "Formulieren",
                      "key": "kuta5ko8q8",
                      "isDeprecated": false,
                      "rightColumn": 64,
                      "textAlign": "CENTER",
                      "dynamicHeight": "FIXED",
                      "widgetId": "j5kj1cuq57",
                      "isVisible": true,
                      "fontStyle": "BOLD",
                      "textColor": "#231F20",
                      "version": 1,
                      "parentId": "016zeofrwo",
                      "renderMode": "CANVAS",
                      "isLoading": false,
                      "borderRadius": "{{appsmith.theme.borderRadius.appBorderRadius}}",
                      "maxDynamicHeight": 9000,
                      "fontSize": "1.875rem",
                      "minDynamicHeight": 4
                    },
                    {
                      "widgetName": "Text3Copy",
                      "displayName": "Text",
                      "iconSVG": "/static/media/icon.97c59b523e6f70ba6f40a10fc2c7c5b5.svg",
                      "searchTags": [
                        "typography",
                        "paragraph",
                        "label"
                      ],
                      "topRow": 13,
                      "bottomRow": 18,
                      "parentRowSpace": 10,
                      "type": "TEXT_WIDGET",
                      "hideCard": false,
                      "animateLoading": true,
                      "overflow": "NONE",
                      "fontFamily": "{{appsmith.theme.fontFamily.appFont}}",
                      "parentColumnSpace": 20.0625,
                      "dynamicTriggerPathList": [],
                      "leftColumn": 0,
                      "dynamicBindingPathList": [
                        {
                          "key": "truncateButtonColor"
                        },
                        {
                          "key": "fontFamily"
                        },
                        {
                          "key": "borderRadius"
                        }
                      ],
                      "shouldTruncate": false,
                      "truncateButtonColor": "{{appsmith.theme.colors.primaryColor}}",
                      "text": "Checklist Werkplekinspectie",
                      "key": "96k9w1hys0",
                      "isDeprecated": false,
                      "rightColumn": 64,
                      "disableLink": false,
                      "textAlign": "CENTER",
                      "dynamicHeight": "AUTO_HEIGHT",
                      "widgetId": "uzfatvqwdm",
                      "isVisible": true,
                      "fontStyle": "BOLD",
                      "textColor": "#231F20",
                      "version": 1,
                      "parentId": "016zeofrwo",
                      "renderMode": "CANVAS",
                      "isLoading": false,
                      "originalTopRow": 13,
                      "borderRadius": "{{appsmith.theme.borderRadius.appBorderRadius}}",
                      "maxDynamicHeight": 9000,
                      "originalBottomRow": 18,
                      "fontSize": "1.875rem",
                      "minDynamicHeight": 4
                    }
                  ],
                  "key": "kqsxm1eviv",
                  "isDeprecated": false,
                  "rightColumn": 481.5,
                  "detachFromLayout": true,
                  "widgetId": "016zeofrwo",
                  "containerStyle": "none",
                  "isVisible": true,
                  "version": 1,
                  "parentId": "btic8v0r02",
                  "renderMode": "CANVAS",
                  "isLoading": false
                }
              ],
              "borderWidth": "0",
              "key": "88lyvx631r",
              "backgroundColor": "#F8F9FA",
              "isDeprecated": false,
              "rightColumn": 64,
              "dynamicHeight": "AUTO_HEIGHT",
              "widgetId": "btic8v0r02",
              "containerStyle": "card",
              "isVisible": true,
              "version": 1,
              "parentId": "0",
              "renderMode": "CANVAS",
              "isLoading": false,
              "originalTopRow": 0,
              "borderRadius": "{{appsmith.theme.borderRadius.appBorderRadius}}",
              "maxDynamicHeight": 9000,
              "originalBottomRow": 20,
              "minDynamicHeight": 10
            },
            {
              "boxShadow": "{{appsmith.theme.boxShadow.appBoxShadow}}",
              "borderColor": "#E0DEDE",
              "widgetName": "Form1",
              "isCanvas": true,
              "displayName": "Form",
              "iconSVG": "/static/media/icon.ea3e08d130e59c56867ae40114c10eed.svg",
              "searchTags": [
                "group"
              ],
              "topRow": 26,
              "bottomRow": 120,
              "parentRowSpace": 10,
              "type": "FORM_WIDGET",
              "hideCard": false,
              "shouldScrollContents": true,
              "animateLoading": true,
              "parentColumnSpace": 20.0625,
              "leftColumn": 0,
              "dynamicBindingPathList": [
                {
                  "key": "borderRadius"
                },
                {
                  "key": "boxShadow"
                }
              ],
              "children": [
                {
                  "widgetName": "Canvas1",
                  "displayName": "Canvas",
                  "topRow": 0,
                  "bottomRow": 940,
                  "parentRowSpace": 1,
                  "type": "CANVAS_WIDGET",
                  "canExtend": false,
                  "hideCard": true,
                  "minHeight": 940,
                  "parentColumnSpace": 1,
                  "leftColumn": 0,
                  "dynamicBindingPathList": [],
                  "children": [
                    {
                      "boxShadow": "none",
                      "widgetName": "SelectProject",
                      "isFilterable": true,
                      "dynamicPropertyPathList": [
                        {
                          "key": "isVisible"
                        },
                        {
                          "key": "isRequired"
                        }
                      ],
                      "displayName": "Select",
                      "iconSVG": "/static/media/icon.bd99caba5853ad71e4b3d8daffacb3a2.svg",
                      "labelText": "",
                      "searchTags": [
                        "dropdown"
                      ],
                      "topRow": 1,
                      "bottomRow": 5,
                      "parentRowSpace": 10,
                      "labelWidth": "9",
                      "type": "SELECT_WIDGET",
                      "serverSideFiltering": false,
                      "hideCard": false,
                      "defaultOptionValue": "",
                      "animateLoading": true,
                      "parentColumnSpace": 19.05,
                      "dynamicTriggerPathList": [
                        {
                          "key": "onOptionChange"
                        }
                      ],
                      "leftColumn": 8,
                      "dynamicBindingPathList": [
                        {
                          "key": "accentColor"
                        },
                        {
                          "key": "borderRadius"
                        },
                        {
                          "key": "options"
                        },
                        {
                          "key": "isVisible"
                        },
                        {
                          "key": "isRequired"
                        }
                      ],
                      "labelPosition": "Auto",
                      "options": "{{GetProjects.data}}",
                      "placeholderText": "Kies een project",
                      "isDisabled": false,
                      "key": "jxoo3svvtb",
                      "labelTextSize": "0.875rem",
                      "isRequired": "{{Ordertype.selectedOptionValue == 'Project'}}",
                      "isDeprecated": false,
                      "rightColumn": 38,
                      "dynamicHeight": "FIXED",
                      "widgetId": "eh0gdda0o2",
                      "accentColor": "{{appsmith.theme.colors.primaryColor}}",
                      "isVisible": "{{Ordertype.selectedOptionValue == 'Project'}}",
                      "version": 1,
                      "parentId": "tyue8em2ef",
                      "labelAlignment": "left",
                      "renderMode": "CANVAS",
                      "isLoading": false,
                      "borderRadius": "{{appsmith.theme.borderRadius.appBorderRadius}}",
                      "maxDynamicHeight": 9000,
                      "onOptionChange": "",
                      "minDynamicHeight": 4
                    },
                    {
                      "boxShadow": "none",
                      "widgetName": "Input_WorkorderDescription",
                      "dynamicPropertyPathList": [
                        {
                          "key": "isVisible"
                        },
                        {
                          "key": "isRequired"
                        }
                      ],
                      "displayName": "Input",
                      "iconSVG": "/static/media/icon.9f505595da61a34f563dba82adeb06ec.svg",
                      "searchTags": [
                        "form",
                        "text input",
                        "number",
                        "textarea"
                      ],
                      "topRow": 6,
                      "bottomRow": 10,
                      "parentRowSpace": 10,
                      "labelWidth": 5,
                      "autoFocus": false,
                      "type": "INPUT_WIDGET_V2",
                      "hideCard": false,
                      "animateLoading": true,
                      "parentColumnSpace": 19.75,
                      "dynamicTriggerPathList": [
                        {
                          "key": "onTextChanged"
                        }
                      ],
                      "resetOnSubmit": true,
                      "leftColumn": 21,
                      "dynamicBindingPathList": [
                        {
                          "key": "accentColor"
                        },
                        {
                          "key": "borderRadius"
                        },
                        {
                          "key": "isVisible"
                        },
                        {
                          "key": "isRequired"
                        }
                      ],
                      "labelPosition": "Left",
                      "labelStyle": "",
                      "inputType": "TEXT",
                      "placeholderText": "Naam klant",
                      "isDisabled": false,
                      "key": "9d7u6ga4y6",
                      "labelTextSize": "0.875rem",
                      "isRequired": "{{Ordertype.selectedOptionValue == 'Werkbon'}}",
                      "onTextChanged": "",
                      "isDeprecated": false,
                      "rightColumn": 38,
                      "dynamicHeight": "FIXED",
                      "widgetId": "sl3r2uqin2",
                      "accentColor": "{{appsmith.theme.colors.primaryColor}}",
                      "errorMessage": "Geen trema of accent gebruiken",
                      "isVisible": "{{Ordertype.selectedOptionValue == 'Werkbon'}}",
                      "label": "",
                      "version": 2,
                      "parentId": "tyue8em2ef",
                      "labelAlignment": "left",
                      "renderMode": "CANVAS",
                      "isLoading": false,
                      "regex": "^[a-zA-Z0-9!@#$&()\\\\-`.+,/\\\" ]*$",
                      "borderRadius": "{{appsmith.theme.borderRadius.appBorderRadius}}",
                      "maxDynamicHeight": 9000,
                      "iconAlign": "left",
                      "defaultText": "",
                      "minDynamicHeight": 4
                    },
                    {
                      "boxShadow": "none",
                      "iconSVG": "/static/media/icon.9f505595da61a34f563dba82adeb06ec.svg",
                      "topRow": 6,
                      "tooltip": "",
                      "labelWidth": "9",
                      "type": "INPUT_WIDGET_V2",
                      "animateLoading": true,
                      "resetOnSubmit": true,
                      "leftColumn": 8,
                      "dynamicBindingPathList": [
                        {
                          "key": "accentColor"
                        },
                        {
                          "key": "borderRadius"
                        },
                        {
                          "key": "isVisible"
                        },
                        {
                          "key": "defaultText"
                        },
                        {
                          "key": "isRequired"
                        }
                      ],
                      "labelStyle": "",
                      "inputType": "TEXT",
                      "placeholderText": "Voer een Werkbonnummer in",
                      "isDisabled": false,
                      "isRequired": "{{Ordertype.selectedOptionValue == 'Werkbon'}}",
                      "dynamicHeight": "FIXED",
                      "accentColor": "{{appsmith.theme.colors.primaryColor}}",
                      "isVisible": "{{Ordertype.selectedOptionValue == 'Werkbon'}}",
                      "version": 2,
                      "isLoading": false,
                      "regex": "[WB]{2}\\d{6}$",
                      "borderRadius": "{{appsmith.theme.borderRadius.appBorderRadius}}",
                      "widgetName": "Input_Workorder",
                      "dynamicPropertyPathList": [
                        {
                          "key": "isVisible"
                        },
                        {
                          "key": "isRequired"
                        }
                      ],
                      "displayName": "Input",
                      "searchTags": [
                        "form",
                        "text input",
                        "number",
                        "textarea"
                      ],
                      "bottomRow": 10,
                      "parentRowSpace": 10,
                      "autoFocus": false,
                      "hideCard": false,
                      "parentColumnSpace": 19.75,
                      "dynamicTriggerPathList": [
                        {
                          "key": "onTextChanged"
                        }
                      ],
                      "labelPosition": "Left",
                      "key": "jq49sqwq06",
                      "labelTextSize": "0.875rem",
                      "onTextChanged": "",
                      "isDeprecated": false,
                      "rightColumn": 21,
                      "widgetId": "2lcb1l8qo5",
                      "errorMessage": "Geen geldige Werkbonnummer",
                      "label": "",
                      "parentId": "tyue8em2ef",
                      "labelAlignment": "left",
                      "renderMode": "CANVAS",
                      "maxDynamicHeight": 9000,
                      "iconAlign": "left",
                      "defaultText": "{{Ordertype.selectedOptionValue == 'Werkbon' ? 'WB' : ''}}",
                      "minDynamicHeight": 4
                    },
                    {
                      "boxShadow": "none",
                      "widgetName": "Ordertype",
                      "dynamicPropertyPathList": [
                        {
                          "key": "onSelectionChange"
                        }
                      ],
                      "displayName": "Radio Group",
                      "iconSVG": "/static/media/icon.ba2b2ee006e51a5c681d7964d7777481.svg",
                      "searchTags": [
                        "choice"
                      ],
                      "topRow": 2,
                      "bottomRow": 10,
                      "parentRowSpace": 10,
                      "labelWidth": 5,
                      "type": "RADIO_GROUP_WIDGET",
                      "hideCard": false,
                      "defaultOptionValue": "Project",
                      "animateLoading": true,
                      "parentColumnSpace": 18.1826171875,
                      "dynamicTriggerPathList": [
                        {
                          "key": "onSelectionChange"
                        }
                      ],
                      "leftColumn": 1,
                      "dynamicBindingPathList": [
                        {
                          "key": "accentColor"
                        }
                      ],
                      "labelPosition": "Top",
                      "onSelectionChange": "{{\nUpdateOrderType.run()\n\t.then(() => {\nresetWidget(\"Input_Workorder\",true);\nresetWidget(\"SelectProject\", true)\t\nresetWidget(\"Input_WorkorderDescription\", true);\t\n}) \n}}\n",
                      "options": [
                        {
                          "label": "Project",
                          "value": "Project"
                        },
                        {
                          "label": "Werkbon",
                          "value": "Werkbon"
                        }
                      ],
                      "isDisabled": false,
                      "key": "wu1ps01u6f",
                      "labelTextSize": "0.875rem",
                      "isRequired": false,
                      "isDeprecated": false,
                      "rightColumn": 7,
                      "dynamicHeight": "FIXED",
                      "widgetId": "o621ygbsql",
                      "accentColor": "{{appsmith.theme.colors.primaryColor}}",
                      "isVisible": true,
                      "label": "",
                      "version": 1,
                      "parentId": "tyue8em2ef",
                      "labelAlignment": "left",
                      "renderMode": "CANVAS",
                      "isLoading": false,
                      "maxDynamicHeight": 9000,
                      "isInline": false,
                      "alignment": "left",
                      "minDynamicHeight": 4
                    },
                    {
                      "boxShadow": "none",
                      "widgetName": "Input1CopyCopyCopyCopyCopyCopyCopy",
                      "displayName": "Input",
                      "iconSVG": "/static/media/icon.9f505595da61a34f563dba82adeb06ec.svg",
                      "searchTags": [
                        "form",
                        "text input",
                        "number",
                        "textarea"
                      ],
                      "topRow": 21,
                      "bottomRow": 25,
                      "parentRowSpace": 10,
                      "labelWidth": "9",
                      "autoFocus": false,
                      "type": "INPUT_WIDGET_V2",
                      "hideCard": false,
                      "animateLoading": true,
                      "parentColumnSpace": 19.75,
                      "dynamicTriggerPathList": [],
                      "resetOnSubmit": true,
                      "leftColumn": 32,
                      "dynamicBindingPathList": [
                        {
                          "key": "accentColor"
                        },
                        {
                          "key": "borderRadius"
                        }
                      ],
                      "labelPosition": "Left",
                      "labelStyle": "",
                      "inputType": "NUMBER",
                      "isDisabled": false,
                      "key": "x3fdwzj212",
                      "labelTextSize": "0.875rem",
                      "isRequired": true,
                      "isDeprecated": false,
                      "rightColumn": 52,
                      "dynamicHeight": "FIXED",
                      "widgetId": "hrxgd2uzz8",
                      "accentColor": "{{appsmith.theme.colors.primaryColor}}",
                      "isVisible": true,
                      "label": "Aantal overige aanwezigen",
                      "version": 2,
                      "parentId": "tyue8em2ef",
                      "labelAlignment": "left",
                      "renderMode": "CANVAS",
                      "isLoading": false,
                      "originalTopRow": 21,
                      "borderRadius": "{{appsmith.theme.borderRadius.appBorderRadius}}",
                      "maxDynamicHeight": 9000,
                      "originalBottomRow": 25,
                      "iconAlign": "left",
                      "defaultText": "",
                      "minDynamicHeight": 4
                    },
                    {
                      "boxShadow": "none",
                      "widgetName": "Input1CopyCopyCopyCopyCopyCopy",
                      "displayName": "Input",
                      "iconSVG": "/static/media/icon.9f505595da61a34f563dba82adeb06ec.svg",
                      "searchTags": [
                        "form",
                        "text input",
                        "number",
                        "textarea"
                      ],
                      "topRow": 16,
                      "bottomRow": 20,
                      "parentRowSpace": 10,
                      "labelWidth": "6",
                      "autoFocus": false,
                      "type": "INPUT_WIDGET_V2",
                      "hideCard": false,
                      "animateLoading": true,
                      "parentColumnSpace": 19.75,
                      "dynamicTriggerPathList": [],
                      "resetOnSubmit": true,
                      "leftColumn": 32,
                      "dynamicBindingPathList": [
                        {
                          "key": "accentColor"
                        },
                        {
                          "key": "borderRadius"
                        }
                      ],
                      "labelPosition": "Left",
                      "labelStyle": "",
                      "inputType": "TEXT",
                      "isDisabled": false,
                      "key": "x3fdwzj212",
                      "labelTextSize": "0.875rem",
                      "isRequired": true,
                      "isDeprecated": false,
                      "rightColumn": 52,
                      "dynamicHeight": "FIXED",
                      "widgetId": "feygdrekrh",
                      "accentColor": "{{appsmith.theme.colors.primaryColor}}",
                      "isVisible": true,
                      "label": "Keetwagen nr.:",
                      "version": 2,
                      "parentId": "tyue8em2ef",
                      "labelAlignment": "left",
                      "renderMode": "CANVAS",
                      "isLoading": false,
                      "originalTopRow": 16,
                      "borderRadius": "{{appsmith.theme.borderRadius.appBorderRadius}}",
                      "maxDynamicHeight": 9000,
                      "originalBottomRow": 20,
                      "iconAlign": "left",
                      "defaultText": "",
                      "minDynamicHeight": 4
                    },
                    {
                      "boxShadow": "none",
                      "widgetName": "Input1CopyCopyCopy",
                      "displayName": "Input",
                      "iconSVG": "/static/media/icon.9f505595da61a34f563dba82adeb06ec.svg",
                      "searchTags": [
                        "form",
                        "text input",
                        "number",
                        "textarea"
                      ],
                      "topRow": 21,
                      "bottomRow": 25,
                      "parentRowSpace": 10,
                      "labelWidth": "16",
                      "autoFocus": false,
                      "type": "INPUT_WIDGET_V2",
                      "hideCard": false,
                      "animateLoading": true,
                      "parentColumnSpace": 19.75,
                      "dynamicTriggerPathList": [],
                      "resetOnSubmit": true,
                      "leftColumn": 1,
                      "dynamicBindingPathList": [
                        {
                          "key": "accentColor"
                        },
                        {
                          "key": "borderRadius"
                        }
                      ],
                      "labelPosition": "Left",
                      "labelStyle": "",
                      "inputType": "NUMBER",
                      "isDisabled": false,
                      "key": "x3fdwzj212",
                      "labelTextSize": "0.875rem",
                      "isRequired": true,
                      "isDeprecated": false,
                      "rightColumn": 31,
                      "dynamicHeight": "FIXED",
                      "widgetId": "025r9admbl",
                      "accentColor": "{{appsmith.theme.colors.primaryColor}}",
                      "isVisible": true,
                      "label": "Aantal Medewerkers Barendrecht-Elektra b.v.",
                      "version": 2,
                      "parentId": "tyue8em2ef",
                      "labelAlignment": "left",
                      "renderMode": "CANVAS",
                      "isLoading": false,
                      "borderRadius": "{{appsmith.theme.borderRadius.appBorderRadius}}",
                      "maxDynamicHeight": 9000,
                      "iconAlign": "left",
                      "defaultText": "",
                      "minDynamicHeight": 4
                    },
                    {
                      "boxShadow": "none",
                      "widgetName": "Input1CopyCopy",
                      "displayName": "Input",
                      "iconSVG": "/static/media/icon.9f505595da61a34f563dba82adeb06ec.svg",
                      "searchTags": [
                        "form",
                        "text input",
                        "number",
                        "textarea"
                      ],
                      "topRow": 16,
                      "bottomRow": 20,
                      "parentRowSpace": 10,
                      "labelWidth": "7",
                      "autoFocus": false,
                      "type": "INPUT_WIDGET_V2",
                      "hideCard": false,
                      "animateLoading": true,
                      "parentColumnSpace": 19.75,
                      "dynamicTriggerPathList": [],
                      "resetOnSubmit": true,
                      "leftColumn": 1,
                      "dynamicBindingPathList": [
                        {
                          "key": "accentColor"
                        },
                        {
                          "key": "borderRadius"
                        }
                      ],
                      "labelPosition": "Left",
                      "labelStyle": "",
                      "inputType": "TEXT",
                      "isDisabled": false,
                      "key": "x3fdwzj212",
                      "labelTextSize": "0.875rem",
                      "isRequired": true,
                      "isDeprecated": false,
                      "rightColumn": 31,
                      "dynamicHeight": "FIXED",
                      "widgetId": "6bkwomws6x",
                      "accentColor": "{{appsmith.theme.colors.primaryColor}}",
                      "isVisible": true,
                      "label": "Werkplekinspecteur",
                      "version": 2,
                      "parentId": "tyue8em2ef",
                      "labelAlignment": "left",
                      "renderMode": "CANVAS",
                      "isLoading": false,
                      "borderRadius": "{{appsmith.theme.borderRadius.appBorderRadius}}",
                      "maxDynamicHeight": 9000,
                      "iconAlign": "left",
                      "defaultText": "",
                      "minDynamicHeight": 4
                    },
                    {
                      "boxShadow": "none",
                      "widgetName": "Input1Copy",
                      "displayName": "Input",
                      "iconSVG": "/static/media/icon.9f505595da61a34f563dba82adeb06ec.svg",
                      "searchTags": [
                        "form",
                        "text input",
                        "number",
                        "textarea"
                      ],
                      "topRow": 11,
                      "bottomRow": 15,
                      "parentRowSpace": 10,
                      "labelWidth": "7",
                      "autoFocus": false,
                      "type": "INPUT_WIDGET_V2",
                      "hideCard": false,
                      "animateLoading": true,
                      "parentColumnSpace": 19.75,
                      "dynamicTriggerPathList": [],
                      "resetOnSubmit": true,
                      "leftColumn": 1,
                      "dynamicBindingPathList": [
                        {
                          "key": "accentColor"
                        },
                        {
                          "key": "borderRadius"
                        }
                      ],
                      "labelPosition": "Left",
                      "labelStyle": "",
                      "inputType": "TEXT",
                      "isDisabled": false,
                      "key": "x3fdwzj212",
                      "labelTextSize": "0.875rem",
                      "isRequired": true,
                      "isDeprecated": false,
                      "rightColumn": 31,
                      "dynamicHeight": "FIXED",
                      "widgetId": "pe8pji5lg6",
                      "accentColor": "{{appsmith.theme.colors.primaryColor}}",
                      "isVisible": true,
                      "label": "Opdrachtgever",
                      "version": 2,
                      "parentId": "tyue8em2ef",
                      "labelAlignment": "left",
                      "renderMode": "CANVAS",
                      "isLoading": false,
                      "borderRadius": "{{appsmith.theme.borderRadius.appBorderRadius}}",
                      "maxDynamicHeight": 9000,
                      "iconAlign": "left",
                      "defaultText": "",
                      "minDynamicHeight": 4
                    },
                    {
                      "resetFormOnClick": true,
                      "boxShadow": "none",
                      "widgetName": "Button1",
                      "buttonColor": "{{appsmith.theme.colors.primaryColor}}",
                      "dynamicPropertyPathList": [
                        {
                          "key": "isDisabled"
                        }
                      ],
                      "displayName": "Button",
                      "iconSVG": "/static/media/icon.cca026338f1c8eb6df8ba03d084c2fca.svg",
                      "searchTags": [
                        "click",
                        "submit"
                      ],
                      "topRow": 88,
                      "bottomRow": 92,
                      "type": "BUTTON_WIDGET",
                      "hideCard": false,
                      "animateLoading": true,
                      "dynamicTriggerPathList": [],
                      "leftColumn": 47,
                      "dynamicBindingPathList": [
                        {
                          "key": "buttonColor"
                        },
                        {
                          "key": "borderRadius"
                        },
                        {
                          "key": "isDisabled"
                        }
                      ],
                      "text": "versturen",
                      "isDisabled": "{{ (Table1.updatedRows.length != GetFormContent.data.length) \n|| Table1.updatedRows.some(question => question.updatedFields.status == null)\n}}",
                      "key": "ssl265yfxn",
                      "isDeprecated": false,
                      "rightColumn": 59,
                      "isDefaultClickDisabled": true,
                      "widgetId": "ghhgi8zie8",
                      "isVisible": true,
                      "recaptchaType": "V3",
                      "version": 1,
                      "parentId": "tyue8em2ef",
                      "renderMode": "CANVAS",
                      "isLoading": false,
                      "originalTopRow": 88,
                      "disabledWhenInvalid": true,
                      "borderRadius": "{{appsmith.theme.borderRadius.appBorderRadius}}",
                      "originalBottomRow": 92,
                      "buttonVariant": "PRIMARY",
                      "placement": "CENTER"
                    },
                    {
                      "boxShadow": "none",
                      "dateFormat": "DD-MM-YYYY HH:mm",
                      "iconSVG": "/static/media/icon.300e5ab8e2e1c26c7a0bad06116842b7.svg",
                      "topRow": 11,
                      "labelWidth": "6",
                      "type": "DATE_PICKER_WIDGET2",
                      "animateLoading": true,
                      "leftColumn": 32,
                      "dynamicBindingPathList": [
                        {
                          "key": "accentColor"
                        },
                        {
                          "key": "borderRadius"
                        },
                        {
                          "key": "defaultDate"
                        }
                      ],
                      "isDisabled": false,
                      "isRequired": true,
                      "dynamicHeight": "FIXED",
                      "accentColor": "{{appsmith.theme.colors.primaryColor}}",
                      "isVisible": true,
                      "datePickerType": "DATE_PICKER",
                      "version": 2,
                      "isLoading": false,
                      "timePrecision": "minute",
                      "borderRadius": "{{appsmith.theme.borderRadius.appBorderRadius}}",
                      "originalBottomRow": 15,
                      "closeOnSelection": true,
                      "widgetName": "DatePicker1",
                      "minDate": "1920-12-31T18:30:00.000Z",
                      "dynamicPropertyPathList": [
                        {
                          "key": "defaultDate"
                        },
                        {
                          "key": "dateFormat"
                        }
                      ],
                      "displayName": "DatePicker",
                      "searchTags": [
                        "calendar"
                      ],
                      "bottomRow": 15,
                      "shortcuts": false,
                      "parentRowSpace": 10,
                      "hideCard": false,
                      "parentColumnSpace": 19.75,
                      "dynamicTriggerPathList": [],
                      "labelPosition": "Left",
                      "key": "cqhpat6ah6",
                      "labelTextSize": "0.875rem",
                      "defaultDate": "{{moment()}}",
                      "isDeprecated": false,
                      "rightColumn": 52,
                      "widgetId": "szluau1avl",
                      "label": "Datum",
                      "parentId": "tyue8em2ef",
                      "labelAlignment": "left",
                      "renderMode": "CANVAS",
                      "originalTopRow": 11,
                      "maxDynamicHeight": 9000,
                      "firstDayOfWeek": "1",
                      "maxDate": "2121-12-31T18:29:00.000Z",
                      "minDynamicHeight": 4
                    },
                    {
                      "boxShadow": "{{appsmith.theme.boxShadow.appBoxShadow}}",
                      "borderColor": "#E0DEDE",
                      "isVisibleDownload": false,
                      "iconSVG": "/static/media/icon.db8a9cbd2acd22a31ea91cc37ea2a46c.svg",
                      "topRow": 28,
                      "isSortable": false,
                      "type": "TABLE_WIDGET_V2",
                      "inlineEditingSaveOption": "CUSTOM",
                      "animateLoading": true,
                      "dynamicBindingPathList": [
                        {
                          "key": "accentColor"
                        },
                        {
                          "key": "borderRadius"
                        },
                        {
                          "key": "boxShadow"
                        },
                        {
                          "key": "tableData"
                        },
                        {
                          "key": "primaryColumns.id.computedValue"
                        },
                        {
                          "key": "primaryColumns.form_id.computedValue"
                        },
                        {
                          "key": "primaryColumns.form_question.computedValue"
                        },
                        {
                          "key": "primaryColumns.created_date.computedValue"
                        },
                        {
                          "key": "primaryColumns.last_modified_date.computedValue"
                        },
                        {
                          "key": "primaryColumns.created_by.computedValue"
                        },
                        {
                          "key": "primaryColumns.answer_type.computedValue"
                        },
                        {
                          "key": "primaryColumns.list_properties.computedValue"
                        },
                        {
                          "key": "primaryColumns.category.computedValue"
                        },
                        {
                          "key": "primaryColumns.status.computedValue"
                        },
                        {
                          "key": "primaryColumns.remark.computedValue"
                        }
                      ],
                      "leftColumn": 1,
                      "delimiter": ",",
                      "defaultSelectedRowIndex": 0,
                      "showInlineEditingOptionDropdown": true,
                      "accentColor": "{{appsmith.theme.colors.primaryColor}}",
                      "isVisibleFilters": false,
                      "isVisible": true,
                      "enableClientSideSearch": false,
                      "version": 1,
                      "totalRecordsCount": 0,
                      "isLoading": false,
                      "childStylesheet": {
                        "button": {
                          "buttonColor": "{{appsmith.theme.colors.primaryColor}}",
                          "borderRadius": "{{appsmith.theme.borderRadius.appBorderRadius}}",
                          "boxShadow": "none"
                        },
                        "menuButton": {
                          "menuColor": "{{appsmith.theme.colors.primaryColor}}",
                          "borderRadius": "{{appsmith.theme.borderRadius.appBorderRadius}}",
                          "boxShadow": "none"
                        },
                        "iconButton": {
                          "buttonColor": "{{appsmith.theme.colors.primaryColor}}",
                          "borderRadius": "{{appsmith.theme.borderRadius.appBorderRadius}}",
                          "boxShadow": "none"
                        },
                        "editActions": {
                          "saveButtonColor": "{{appsmith.theme.colors.primaryColor}}",
                          "saveBorderRadius": "{{appsmith.theme.borderRadius.appBorderRadius}}",
                          "discardButtonColor": "{{appsmith.theme.colors.primaryColor}}",
                          "discardBorderRadius": "{{appsmith.theme.borderRadius.appBorderRadius}}"
                        }
                      },
                      "borderRadius": "{{appsmith.theme.borderRadius.appBorderRadius}}",
                      "defaultSelectedRowIndices": [
                        0
                      ],
                      "widgetName": "Table1",
                      "defaultPageSize": 0,
                      "columnOrder": [
                        "category",
                        "form_question",
                        "status",
                        "remark",
                        "id",
                        "form_id",
                        "created_date",
                        "last_modified_date",
                        "created_by",
                        "answer_type",
                        "list_properties"
                      ],
                      "dynamicPropertyPathList": [],
                      "displayName": "Table",
                      "bottomRow": 80,
                      "columnWidthMap": {
                        "task": 245,
                        "step": 62,
                        "status": 321,
                        "form_question": 228
                      },
                      "parentRowSpace": 10,
                      "hideCard": false,
                      "parentColumnSpace": 19.75,
                      "dynamicTriggerPathList": [],
                      "borderWidth": "1",
                      "primaryColumns": {
                        "id": {
                          "allowCellWrapping": false,
                          "index": 0,
                          "width": 150,
                          "originalId": "id",
                          "id": "id",
                          "alias": "id",
                          "horizontalAlignment": "LEFT",
                          "verticalAlignment": "CENTER",
                          "columnType": "number",
                          "textColor": "",
                          "textSize": "0.875rem",
                          "fontStyle": "",
                          "enableFilter": true,
                          "enableSort": true,
                          "isVisible": false,
                          "isDisabled": false,
                          "isCellEditable": false,
                          "isEditable": false,
                          "isCellVisible": true,
                          "isDerived": false,
                          "label": "id",
                          "isSaveVisible": true,
                          "isDiscardVisible": true,
                          "computedValue": "{{Table1.processedTableData.map((currentRow, currentIndex) => ( currentRow[\"id\"]))}}",
                          "validation": {},
                          "cellBackground": ""
                        },
                        "form_id": {
                          "allowCellWrapping": false,
                          "index": 1,
                          "width": 150,
                          "originalId": "form_id",
                          "id": "form_id",
                          "alias": "form_id",
                          "horizontalAlignment": "LEFT",
                          "verticalAlignment": "CENTER",
                          "columnType": "number",
                          "textColor": "",
                          "textSize": "0.875rem",
                          "fontStyle": "",
                          "enableFilter": true,
                          "enableSort": true,
                          "isVisible": false,
                          "isDisabled": false,
                          "isCellEditable": false,
                          "isEditable": false,
                          "isCellVisible": true,
                          "isDerived": false,
                          "label": "form_id",
                          "isSaveVisible": true,
                          "isDiscardVisible": true,
                          "computedValue": "{{Table1.processedTableData.map((currentRow, currentIndex) => ( currentRow[\"form_id\"]))}}",
                          "validation": {},
                          "cellBackground": ""
                        },
                        "form_question": {
                          "allowCellWrapping": false,
                          "index": 2,
                          "width": 150,
                          "originalId": "form_question",
                          "id": "form_question",
                          "alias": "form_question",
                          "horizontalAlignment": "LEFT",
                          "verticalAlignment": "CENTER",
                          "columnType": "text",
                          "textColor": "",
                          "textSize": "0.875rem",
                          "fontStyle": "",
                          "enableFilter": true,
                          "enableSort": true,
                          "isVisible": true,
                          "isDisabled": false,
                          "isCellEditable": false,
                          "isEditable": false,
                          "isCellVisible": true,
                          "isDerived": false,
                          "label": "Inspectiepunten",
                          "isSaveVisible": true,
                          "isDiscardVisible": true,
                          "computedValue": "{{Table1.processedTableData.map((currentRow, currentIndex) => ( currentRow[\"form_question\"]))}}",
                          "validation": {},
                          "cellBackground": ""
                        },
                        "created_date": {
                          "allowCellWrapping": false,
                          "index": 3,
                          "width": 150,
                          "originalId": "created_date",
                          "id": "created_date",
                          "alias": "created_date",
                          "horizontalAlignment": "LEFT",
                          "verticalAlignment": "CENTER",
                          "columnType": "text",
                          "textColor": "",
                          "textSize": "0.875rem",
                          "fontStyle": "",
                          "enableFilter": true,
                          "enableSort": true,
                          "isVisible": false,
                          "isDisabled": false,
                          "isCellEditable": false,
                          "isEditable": false,
                          "isCellVisible": true,
                          "isDerived": false,
                          "label": "created_date",
                          "isSaveVisible": true,
                          "isDiscardVisible": true,
                          "computedValue": "{{Table1.processedTableData.map((currentRow, currentIndex) => ( currentRow[\"created_date\"]))}}",
                          "validation": {},
                          "cellBackground": ""
                        },
                        "last_modified_date": {
                          "allowCellWrapping": false,
                          "index": 4,
                          "width": 150,
                          "originalId": "last_modified_date",
                          "id": "last_modified_date",
                          "alias": "last_modified_date",
                          "horizontalAlignment": "LEFT",
                          "verticalAlignment": "CENTER",
                          "columnType": "text",
                          "textColor": "",
                          "textSize": "0.875rem",
                          "fontStyle": "",
                          "enableFilter": true,
                          "enableSort": true,
                          "isVisible": false,
                          "isDisabled": false,
                          "isCellEditable": false,
                          "isEditable": false,
                          "isCellVisible": true,
                          "isDerived": false,
                          "label": "last_modified_date",
                          "isSaveVisible": true,
                          "isDiscardVisible": true,
                          "computedValue": "{{Table1.processedTableData.map((currentRow, currentIndex) => ( currentRow[\"last_modified_date\"]))}}",
                          "validation": {},
                          "cellBackground": ""
                        },
                        "created_by": {
                          "allowCellWrapping": false,
                          "index": 5,
                          "width": 150,
                          "originalId": "created_by",
                          "id": "created_by",
                          "alias": "created_by",
                          "horizontalAlignment": "LEFT",
                          "verticalAlignment": "CENTER",
                          "columnType": "text",
                          "textColor": "",
                          "textSize": "0.875rem",
                          "fontStyle": "",
                          "enableFilter": true,
                          "enableSort": true,
                          "isVisible": false,
                          "isDisabled": false,
                          "isCellEditable": false,
                          "isEditable": false,
                          "isCellVisible": true,
                          "isDerived": false,
                          "label": "created_by",
                          "isSaveVisible": true,
                          "isDiscardVisible": true,
                          "computedValue": "{{Table1.processedTableData.map((currentRow, currentIndex) => ( currentRow[\"created_by\"]))}}",
                          "validation": {},
                          "cellBackground": ""
                        },
                        "answer_type": {
                          "allowCellWrapping": false,
                          "index": 6,
                          "width": 150,
                          "originalId": "answer_type",
                          "id": "answer_type",
                          "alias": "answer_type",
                          "horizontalAlignment": "LEFT",
                          "verticalAlignment": "CENTER",
                          "columnType": "text",
                          "textColor": "",
                          "textSize": "0.875rem",
                          "fontStyle": "",
                          "enableFilter": true,
                          "enableSort": true,
                          "isVisible": false,
                          "isDisabled": false,
                          "isCellEditable": false,
                          "isEditable": false,
                          "isCellVisible": true,
                          "isDerived": false,
                          "label": "answer_type",
                          "isSaveVisible": true,
                          "isDiscardVisible": true,
                          "computedValue": "{{Table1.processedTableData.map((currentRow, currentIndex) => ( currentRow[\"answer_type\"]))}}",
                          "validation": {},
                          "cellBackground": ""
                        },
                        "list_properties": {
                          "allowCellWrapping": false,
                          "index": 7,
                          "width": 150,
                          "originalId": "list_properties",
                          "id": "list_properties",
                          "alias": "list_properties",
                          "horizontalAlignment": "LEFT",
                          "verticalAlignment": "CENTER",
                          "columnType": "text",
                          "textColor": "",
                          "textSize": "0.875rem",
                          "fontStyle": "",
                          "enableFilter": true,
                          "enableSort": true,
                          "isVisible": false,
                          "isDisabled": false,
                          "isCellEditable": false,
                          "isEditable": false,
                          "isCellVisible": true,
                          "isDerived": false,
                          "label": "list_properties",
                          "isSaveVisible": true,
                          "isDiscardVisible": true,
                          "computedValue": "{{Table1.processedTableData.map((currentRow, currentIndex) => ( currentRow[\"list_properties\"]))}}",
                          "validation": {},
                          "cellBackground": ""
                        },
                        "category": {
                          "allowCellWrapping": false,
                          "index": 10,
                          "width": 150,
                          "originalId": "category",
                          "id": "category",
                          "alias": "category",
                          "horizontalAlignment": "LEFT",
                          "verticalAlignment": "CENTER",
                          "columnType": "text",
                          "textColor": "",
                          "textSize": "0.875rem",
                          "fontStyle": "",
                          "enableFilter": true,
                          "enableSort": true,
                          "isVisible": true,
                          "isDisabled": false,
                          "isCellEditable": false,
                          "isEditable": false,
                          "isCellVisible": true,
                          "isDerived": false,
                          "label": "",
                          "isSaveVisible": true,
                          "isDiscardVisible": true,
                          "computedValue": "{{Table1.processedTableData.map((currentRow, currentIndex) => ( currentRow[\"category\"]))}}",
                          "validation": {},
                          "cellBackground": ""
                        },
                        "status": {
                          "allowCellWrapping": false,
                          "index": 8,
                          "width": 150,
                          "originalId": "status",
                          "id": "status",
                          "alias": "status",
                          "horizontalAlignment": "LEFT",
                          "verticalAlignment": "CENTER",
                          "columnType": "select",
                          "textColor": "",
                          "textSize": "0.875rem",
                          "fontStyle": "",
                          "enableFilter": true,
                          "enableSort": true,
                          "isVisible": true,
                          "isDisabled": false,
                          "isCellEditable": true,
                          "isEditable": true,
                          "isCellVisible": true,
                          "isDerived": false,
                          "label": "Status (OK/NOK/NVT)",
                          "isSaveVisible": true,
                          "isDiscardVisible": true,
                          "computedValue": "{{Table1.processedTableData.map((currentRow, currentIndex) => ( currentRow[\"status\"]))}}",
                          "validation": {},
                          "cellBackground": "",
                          "selectOptions": "[\n{\n\"label\":\"OK\"\n,\"value\":\"OK\"\n},\n{\n\"label\":\"NOK\"\n,\"value\":\"NOK\"\n},\n{\n\"label\":\"NVT\"\n,\"value\":\"NVT\"\n}\n]"
                        },
                        "remark": {
                          "allowCellWrapping": false,
                          "index": 9,
                          "width": 150,
                          "originalId": "remark",
                          "id": "remark",
                          "alias": "remark",
                          "horizontalAlignment": "LEFT",
                          "verticalAlignment": "CENTER",
                          "columnType": "text",
                          "textColor": "",
                          "textSize": "0.875rem",
                          "fontStyle": "",
                          "enableFilter": true,
                          "enableSort": true,
                          "isVisible": true,
                          "isDisabled": false,
                          "isCellEditable": true,
                          "isEditable": true,
                          "isCellVisible": true,
                          "isDerived": false,
                          "label": "Opmerkingen / afwijkingen",
                          "isSaveVisible": true,
                          "isDiscardVisible": true,
                          "computedValue": "{{Table1.processedTableData.map((currentRow, currentIndex) => ( currentRow[\"remark\"]))}}",
                          "validation": {},
                          "cellBackground": ""
                        }
                      },
                      "key": "wcghxnqulu",
                      "isDeprecated": false,
                      "rightColumn": 63,
                      "textSize": "0.875rem",
                      "widgetId": "hq6txrwgkh",
                      "tableData": "{{GetFormContent.data}}",
                      "label": "Data",
                      "searchKey": "",
                      "parentId": "tyue8em2ef",
                      "renderMode": "CANVAS",
                      "horizontalAlignment": "LEFT",
                      "isVisibleSearch": false,
                      "isVisiblePagination": false,
                      "verticalAlignment": "CENTER"
                    }
                  ],
                  "key": "fdecgpd0i3",
                  "isDeprecated": false,
                  "rightColumn": 481.5,
                  "detachFromLayout": true,
                  "widgetId": "tyue8em2ef",
                  "containerStyle": "none",
                  "isVisible": true,
                  "version": 1,
                  "parentId": "w0h64xnbc1",
                  "renderMode": "CANVAS",
                  "isLoading": false
                }
              ],
              "borderWidth": "1",
              "key": "949zbm89fq",
              "backgroundColor": "#FFFFFF",
              "isDeprecated": false,
              "rightColumn": 64,
              "dynamicHeight": "AUTO_HEIGHT",
              "widgetId": "w0h64xnbc1",
              "isVisible": true,
              "parentId": "0",
              "renderMode": "CANVAS",
              "isLoading": false,
              "originalTopRow": 26,
              "borderRadius": "{{appsmith.theme.borderRadius.appBorderRadius}}",
              "maxDynamicHeight": 9000,
              "originalBottomRow": 120,
              "minDynamicHeight": 10
            },
            {
              "boxShadow": "none",
              "widgetName": "IconButton1",
              "onClick": "{{navigateTo('Formulieren - Overzicht', {}, 'SAME_WINDOW')}}",
              "buttonColor": "{{appsmith.theme.colors.primaryColor}}",
              "displayName": "Icon Button",
              "iconSVG": "/static/media/icon.1a0c634ac75f9fa6b6ae7a8df882a3ba.svg",
              "searchTags": [
                "click",
                "submit"
              ],
              "topRow": 21,
              "bottomRow": 25,
              "parentRowSpace": 10,
              "type": "ICON_BUTTON_WIDGET",
              "hideCard": false,
              "animateLoading": true,
              "parentColumnSpace": 20.0625,
              "dynamicTriggerPathList": [
                {
                  "key": "onClick"
                }
              ],
              "leftColumn": 0,
              "dynamicBindingPathList": [
                {
                  "key": "buttonColor"
                },
                {
                  "key": "borderRadius"
                }
              ],
              "isDisabled": false,
              "key": "3g9q5fax4n",
              "isDeprecated": false,
              "rightColumn": 4,
              "iconName": "arrow-left",
              "widgetId": "4o86veiscf",
              "isVisible": true,
              "version": 1,
              "parentId": "0",
              "renderMode": "CANVAS",
              "isLoading": false,
              "originalTopRow": 21,
              "borderRadius": "{{appsmith.theme.borderRadius.appBorderRadius}}",
              "originalBottomRow": 25,
              "buttonVariant": "PRIMARY"
            },
            {
              "widgetName": "Text3",
              "displayName": "Text",
              "iconSVG": "/static/media/icon.97c59b523e6f70ba6f40a10fc2c7c5b5.svg",
              "searchTags": [
                "typography",
                "paragraph",
                "label"
              ],
              "topRow": 132,
              "bottomRow": 164,
              "parentRowSpace": 10,
              "type": "TEXT_WIDGET",
              "hideCard": false,
              "animateLoading": true,
              "overflow": "NONE",
              "fontFamily": "{{appsmith.theme.fontFamily.appFont}}",
              "parentColumnSpace": 20.0625,
              "dynamicTriggerPathList": [],
              "leftColumn": 6,
              "dynamicBindingPathList": [
                {
                  "key": "truncateButtonColor"
                },
                {
                  "key": "fontFamily"
                },
                {
                  "key": "borderRadius"
                },
                {
                  "key": "text"
                }
              ],
              "shouldTruncate": false,
              "truncateButtonColor": "{{appsmith.theme.colors.primaryColor}}",
              "text": "{{Form1.data}}",
              "key": "gpxdajehbp",
              "isDeprecated": false,
              "rightColumn": 22,
              "textAlign": "LEFT",
              "dynamicHeight": "AUTO_HEIGHT",
              "widgetId": "p07a4473m6",
              "isVisible": true,
              "fontStyle": "BOLD",
              "textColor": "#231F20",
              "version": 1,
              "parentId": "0",
              "renderMode": "CANVAS",
              "isLoading": false,
              "originalTopRow": 132,
              "borderRadius": "{{appsmith.theme.borderRadius.appBorderRadius}}",
              "maxDynamicHeight": 9000,
              "originalBottomRow": 156,
              "fontSize": "1rem",
              "minDynamicHeight": 4
            },
            {
              "widgetName": "Text4",
              "displayName": "Text",
              "iconSVG": "/static/media/icon.97c59b523e6f70ba6f40a10fc2c7c5b5.svg",
              "searchTags": [
                "typography",
                "paragraph",
                "label"
              ],
              "topRow": 130,
              "bottomRow": 134,
              "parentRowSpace": 10,
              "type": "TEXT_WIDGET",
              "hideCard": false,
              "animateLoading": true,
              "overflow": "NONE",
              "fontFamily": "{{appsmith.theme.fontFamily.appFont}}",
              "parentColumnSpace": 20.0625,
              "dynamicTriggerPathList": [],
              "leftColumn": 31,
              "dynamicBindingPathList": [
                {
                  "key": "truncateButtonColor"
                },
                {
                  "key": "fontFamily"
                },
                {
                  "key": "borderRadius"
                },
                {
                  "key": "text"
                }
              ],
              "shouldTruncate": false,
              "truncateButtonColor": "{{appsmith.theme.colors.primaryColor}}",
              "text": "{{ (Table1.updatedRows.length != GetFormContent.data.length) \n|| Table1.updatedRows.some(question => question.updatedFields.status == null)\n}}",
              "key": "ppetf1zr19",
              "isDeprecated": false,
              "rightColumn": 47,
              "textAlign": "LEFT",
              "dynamicHeight": "AUTO_HEIGHT",
              "widgetId": "it84duwrb6",
              "isVisible": true,
              "fontStyle": "BOLD",
              "textColor": "#231F20",
              "version": 1,
              "parentId": "0",
              "renderMode": "CANVAS",
              "isLoading": false,
              "originalTopRow": 130,
              "borderRadius": "{{appsmith.theme.borderRadius.appBorderRadius}}",
              "maxDynamicHeight": 9000,
              "originalBottomRow": 134,
              "fontSize": "1rem",
              "minDynamicHeight": 4
            },
            {
              "widgetName": "Text5",
              "displayName": "Text",
              "iconSVG": "/static/media/icon.97c59b523e6f70ba6f40a10fc2c7c5b5.svg",
              "searchTags": [
                "typography",
                "paragraph",
                "label"
              ],
              "topRow": 130,
              "bottomRow": 197,
              "parentRowSpace": 10,
              "type": "TEXT_WIDGET",
              "hideCard": false,
              "animateLoading": true,
              "overflow": "NONE",
              "fontFamily": "{{appsmith.theme.fontFamily.appFont}}",
              "parentColumnSpace": 20.0625,
              "dynamicTriggerPathList": [],
              "leftColumn": 48,
              "dynamicBindingPathList": [
                {
                  "key": "truncateButtonColor"
                },
                {
                  "key": "fontFamily"
                },
                {
                  "key": "borderRadius"
                },
                {
                  "key": "text"
                }
              ],
              "shouldTruncate": false,
              "truncateButtonColor": "{{appsmith.theme.colors.primaryColor}}",
              "text": "{{GetFormContent.data}}",
              "key": "i1ktj9djg6",
              "isDeprecated": false,
              "rightColumn": 64,
              "textAlign": "LEFT",
              "dynamicHeight": "AUTO_HEIGHT",
              "widgetId": "6pd8a41rry",
              "isVisible": true,
              "fontStyle": "BOLD",
              "textColor": "#231F20",
              "version": 1,
              "parentId": "0",
              "renderMode": "CANVAS",
              "isLoading": false,
              "originalTopRow": 130,
              "borderRadius": "{{appsmith.theme.borderRadius.appBorderRadius}}",
              "maxDynamicHeight": 9000,
              "originalBottomRow": 197,
              "fontSize": "1rem",
              "minDynamicHeight": 4
            }
          ]
        },
        "layoutOnLoadActions": [
          [
            {
              "id": "Formulier - Werkplekinspectie_GetFormContent",
              "name": "GetFormContent",
              "confirmBeforeExecute": false,
              "pluginType": "DB",
              "jsonPathKeys": [],
              "timeoutInMillisecond": 10000
            },
            {
              "id": "Formulier - Werkplekinspectie_GetProjects",
              "name": "GetProjects",
              "confirmBeforeExecute": false,
              "pluginType": "DB",
              "jsonPathKeys": [],
              "timeoutInMillisecond": 10000
            }
          ],
          [
            {
              "id": "Formulier - Werkplekinspectie_JS_User.checkSessionID",
              "name": "JS_User.checkSessionID",
              "collectionId": "Formulier - Werkplekinspectie_JS_User",
              "confirmBeforeExecute": false,
              "pluginType": "JS",
              "jsonPathKeys": [
                "() => {\n  if (!appsmith.store?.userSession?.session_id && appsmith.mode != \"EDIT\") {\n    navigateTo(\"Authenticatie\", {}, \"SAME_WINDOW\");\n  } else {\n    JS_User.checkUserLogin();\n  }\n}"
              ],
              "timeoutInMillisecond": 10000
            }
          ]
        ],
        "layoutOnLoadActionErrors": [],
        "validOnPageLoadActions": true,
        "id": "Formulier - Werkplekinspectie",
        "deleted": false,
        "policies": [],
        "userPermissions": []
      }
    ],
    "userPermissions": [],
    "policies": [],
    "isHidden": true
  },
  "deleted": false,
  "gitSyncId": "63aac04e67086437e017196b_63b40f0fb4cde27268a7f783"
}